torchrec/__init__.py
torchrec/streamable.py
torchrec/tensor_types.py
torchrec/types.py
torchrec/version.py
torchrec/datasets/__init__.py
torchrec/datasets/criteo.py
torchrec/datasets/movielens.py
torchrec/datasets/random.py
torchrec/datasets/utils.py
torchrec/datasets/scripts/__init__.py
torchrec/datasets/scripts/contiguous_preproc_criteo.py
torchrec/datasets/scripts/npy_preproc_criteo.py
torchrec/datasets/scripts/shuffle_preproc_criteo.py
torchrec/datasets/test_utils/__init__.py
torchrec/datasets/test_utils/criteo_test_utils.py
torchrec/distributed/__init__.py
torchrec/distributed/batched_embedding_kernel.py
torchrec/distributed/collective_utils.py
torchrec/distributed/comm.py
torchrec/distributed/comm_ops.py
torchrec/distributed/dist_data.py
torchrec/distributed/embedding.py
torchrec/distributed/embedding_dim_bucketer.py
torchrec/distributed/embedding_kernel.py
torchrec/distributed/embedding_lookup.py
torchrec/distributed/embedding_sharding.py
torchrec/distributed/embedding_tower_sharding.py
torchrec/distributed/embedding_types.py
torchrec/distributed/embeddingbag.py
torchrec/distributed/fbgemm_qcomm_codec.py
torchrec/distributed/fp_embeddingbag.py
torchrec/distributed/fused_embedding.py
torchrec/distributed/fused_embeddingbag.py
torchrec/distributed/fused_params.py
torchrec/distributed/global_settings.py
torchrec/distributed/grouped_position_weighted.py
torchrec/distributed/infer_utils.py
torchrec/distributed/itep_embeddingbag.py
torchrec/distributed/keyed_jagged_tensor_pool.py
torchrec/distributed/logger.py
torchrec/distributed/logging_handlers.py
torchrec/distributed/mc_embedding.py
torchrec/distributed/mc_embedding_modules.py
torchrec/distributed/mc_embeddingbag.py
torchrec/distributed/mc_modules.py
torchrec/distributed/model_parallel.py
torchrec/distributed/object_pool.py
torchrec/distributed/quant_embedding.py
torchrec/distributed/quant_embedding_kernel.py
torchrec/distributed/quant_embeddingbag.py
torchrec/distributed/quant_state.py
torchrec-1.4.0.dist-info/licenses/LICENSE
torchrec-1.4.0.dist-info/METADATA
torchrec-1.4.0.dist-info/WHEEL
torchrec-1.4.0.dist-info/top_level.txt
torchrec-1.4.0.dist-info/RECORD
