Metadata-Version: 2.4
Name: torchrec
Version: 1.4.0
Summary: TorchRec: Pytorch library for recommendation systems
Home-page: https://github.com/meta-pytorch/torchrec
Author: TorchRec Team
Author-email: packages@pytorch.org
Maintainer: TroyGarden
Maintainer-email: hhy@meta.com
License: BSD-3
Keywords: pytorch,recommendation systems,sharding,distributed training
Classifier: Development Status :: 5 - Production/Stable
Classifier: Intended Audience :: Developers
Classifier: Intended Audience :: Science/Research
Classifier: License :: OSI Approved :: BSD License
Classifier: Programming Language :: Python :: 3
Classifier: Programming Language :: Python :: 3.10
Classifier: Programming Language :: Python :: 3.11
Classifier: Programming Language :: Python :: 3.12
Classifier: Programming Language :: Python :: 3.13
Classifier: Topic :: Scientific/Engineering :: Artificial Intelligence
Requires-Python: >=3.10
License-File: LICENSE
Requires-Dist: fbgemm-gpu
Requires-Dist: tensordict
Requires-Dist: torchmetrics==1.0.3
Requires-Dist: tqdm
Requires-Dist: pyre-extensions
Requires-Dist: iopath
Dynamic: author
Dynamic: author-email
Dynamic: classifier
Dynamic: description
Dynamic: description-content-type
Dynamic: home-page
Dynamic: keywords
Dynamic: license
Dynamic: license-file
Dynamic: maintainer
Dynamic: maintainer-email
Dynamic: requires-dist
Dynamic: requires-python
Dynamic: summary
